trae_rules_mcp/__init__.py
trae_rules_mcp/main.py
trae_rules_mcp-1.0.1.dist-info/METADATA
trae_rules_mcp-1.0.1.dist-info/WHEEL
trae_rules_mcp-1.0.1.dist-info/licenses/LICENSE
trae_rules_mcp-1.0.1.dist-info/RECORD
