Metadata-Version: 2.4
Name: trae-rules-mcp
Version: 1.0.1
Summary: Trae AI 规则文件生成器 MCP 服务 - 智能生成项目开发规则
Project-URL: Homepage, https://github.com/trae-ai/trae-rules-mcp
Project-URL: Repository, https://github.com/trae-ai/trae-rules-mcp
Project-URL: Issues, https://github.com/trae-ai/trae-rules-mcp/issues
Project-URL: Documentation, https://github.com/trae-ai/trae-rules-mcp#readme
Author-email: Trae AI <support@trae.ai>
License: MIT
License-File: LICENSE
Keywords: ai,development,generator,mcp,rules,trae
Classifier: Development Status :: 5 - Production/Stable
Classifier: Intended Audience :: Developers
Classifier: License :: OSI Approved :: MIT License
Classifier: Operating System :: OS Independent
Classifier: Programming Language :: Python :: 3
Classifier: Programming Language :: Python :: 3.10
Classifier: Programming Language :: Python :: 3.11
Classifier: Programming Language :: Python :: 3.12
Classifier: Topic :: Software Development
Classifier: Topic :: Software Development :: Libraries :: Python Modules
Requires-Python: >=3.10
Requires-Dist: fastapi>=0.104.0
Requires-Dist: mcp>=1.0.0
Requires-Dist: pathlib2>=2.3.0
Requires-Dist: pydantic>=2.0.0
Requires-Dist: uvicorn[standard]>=0.24.0
Provides-Extra: dev
Requires-Dist: black>=23.0.0; extra == 'dev'
Requires-Dist: isort>=5.0.0; extra == 'dev'
Requires-Dist: mypy>=1.0.0; extra == 'dev'
Requires-Dist: pytest>=7.0.0; extra == 'dev'
